append_hygiene_sdk/__init__.py
append_hygiene_sdk/append.py
append_hygiene_sdk/hygiene.py
append_hygiene_sdk/logs/__init__.py
append_hygiene_sdk/logs/logger.py
append_hygiene_sdk-0.2.1.dist-info/WHEEL
append_hygiene_sdk-0.2.1.dist-info/METADATA
append_hygiene_sdk-0.2.1.dist-info/RECORD
