Metadata-Version: 2.1
Name: append-hygiene-sdk
Version: 0.2.1
Summary: Append Hygiene SDK provides a library of classes for working with On-Demand API in your Python code.
Home-page: https://github.com/oneaudience/data-team-append-hygiene-sdk
Author: TheBridgeDan
Author-email: 97176881+TheBridgeDan@users.noreply.github.com
Requires-Python: >=3.6,<4.0
Classifier: Programming Language :: Python :: 3
Classifier: Programming Language :: Python :: 3.10
Classifier: Programming Language :: Python :: 3.6
Classifier: Programming Language :: Python :: 3.7
Classifier: Programming Language :: Python :: 3.8
Classifier: Programming Language :: Python :: 3.9
Requires-Dist: python-dotenv (>=0.20.0,<0.21.0)
Requires-Dist: requests (>=2.27.1,<3.0.0)
Project-URL: Repository, https://github.com/oneaudience/data-team-append-hygiene-sdk
